adafruit_wii_classic.py
adafruit_circuitpython_wii_classic-1.0.11.dist-info/licenses/LICENSE
adafruit_circuitpython_wii_classic-1.0.11.dist-info/METADATA
adafruit_circuitpython_wii_classic-1.0.11.dist-info/WHEEL
adafruit_circuitpython_wii_classic-1.0.11.dist-info/top_level.txt
adafruit_circuitpython_wii_classic-1.0.11.dist-info/RECORD
