Metadata-Version: 2.4
Name: adafruit-circuitpython-wii-classic
Version: 1.0.11
Summary: CircuitPython library for Nintendo Wii Classic controllers.
Author-email: Adafruit Industries <circuitpython@adafruit.com>
License: MIT
Project-URL: Homepage, https://github.com/adafruit/Adafruit_CircuitPython_Wii_Classic
Keywords: adafruit,blinka,circuitpython,micropython,wii_classic,wii,classic,remote,control
Classifier: Intended Audience :: Developers
Classifier: Topic :: Software Development :: Libraries
Classifier: Topic :: Software Development :: Embedded Systems
Classifier: Topic :: System :: Hardware
Classifier: License :: OSI Approved :: MIT License
Classifier: Programming Language :: Python :: 3
License-File: LICENSE
Requires-Dist: Adafruit-Blinka
Requires-Dist: adafruit-circuitpython-busdevice
Provides-Extra: optional
Dynamic: license-file
